pymmails/__init__.py
pymmails/grabber/__init__.py
pymmails/grabber/additional_mime_type.py
pymmails/grabber/email_message.py
pymmails/grabber/mail_exception.py
pymmails/grabber/mailbox_mock.py
pymmails/grabber/mailboximap.py
pymmails/grabber/pop_helper.py
pymmails/helpers/__init__.py
pymmails/helpers/buffer_files_writing.py
pymmails/helpers/helpers_exceptions.py
pymmails/helpers/iter_helper.py
pymmails/render/__init__.py
pymmails/render/email_message_list_renderer.py
pymmails/render/email_message_renderer.py
pymmails/render/email_message_style.py
pymmails/render/renderer.py
pymmails/render/renderer_exceptions.py
pymmails/sender/__init__.py
pymmails/sender/email_sender.py
pymmails-0.3.319.dist-info/LICENSE.txt
pymmails-0.3.319.dist-info/METADATA
pymmails-0.3.319.dist-info/WHEEL
pymmails-0.3.319.dist-info/top_level.txt
pymmails-0.3.319.dist-info/RECORD
