Metadata-Version: 2.1
Name: pymmails
Version: 0.3.319
Summary: A module to download emails from an IMAP4 server
Home-page: http://www.xavierdupre.fr/app/pymmails/helpsphinx/index.html
Author: Xavier Dupré
Author-email: xavier.dupre@gmail.com
License: MIT
Download-URL: https://github.com/sdpython/pymmails/
Keywords: pymmails,synchronization,files,Xavier,Dupré
Platform: UNKNOWN
Classifier: Programming Language :: Python :: 3
Classifier: Intended Audience :: Developers
Classifier: Topic :: Scientific/Engineering
Classifier: Topic :: Education
Classifier: License :: OSI Approved :: MIT License
Classifier: Development Status :: 5 - Production/Stable
Requires-Dist: pyquickhelper
Requires-Dist: pycryptodomex
